django_query_analyzer/__init__.py
django_query_analyzer/parser.py
django_query_analyzer/reporter.py
django_query_index_analyzer-0.1.4.dist-info/METADATA
django_query_index_analyzer-0.1.4.dist-info/WHEEL
django_query_index_analyzer-0.1.4.dist-info/entry_points.txt
django_query_index_analyzer-0.1.4.dist-info/top_level.txt
django_query_index_analyzer-0.1.4.dist-info/RECORD
