Metadata-Version: 2.4
Name: django-query-index-analyzer
Version: 0.1.4
Summary: CLI tool to analyze Django ORM filter, exclude, and annotate usage on a specific model.
Author-email: Marcos Eliziario <opensource@msantos.dev>
License-Expression: MIT
Classifier: Programming Language :: Python :: 3
Classifier: Operating System :: OS Independent
Requires-Python: >=3.8
Requires-Dist: pathspec
